MANIFEST.in
README.rst
setup.py
django_loading.egg-info/PKG-INFO
django_loading.egg-info/SOURCES.txt
django_loading.egg-info/dependency_links.txt
django_loading.egg-info/not-zip-safe
django_loading.egg-info/top_level.txt
loading/__init__.py
loading/apploader.py